pyinfra_etcd/__init__.py
pyinfra_etcd/defaults.py
pyinfra_etcd/etcd.py
pyinfra_etcd/util.py
pyinfra_etcd/templates/etcd.conf.j2
pyinfra_etcd/templates/etcd.service.j2
pyinfra_etcd-0.3.dist-info/METADATA
pyinfra_etcd-0.3.dist-info/WHEEL
pyinfra_etcd-0.3.dist-info/top_level.txt
pyinfra_etcd-0.3.dist-info/RECORD
