Metadata-Version: 2.1
Name: pyinfra-etcd
Version: 0.3
Summary: Install & bootstrap etcd clusters with pyinfra.
Home-page: UNKNOWN
Author: UNKNOWN
Author-email: UNKNOWN
License: UNKNOWN
Platform: UNKNOWN
Requires-Dist: pyinfra (>=0.5)
